calar/__init__.py
calar-2.5.1.dist-info/METADATA
calar-2.5.1.dist-info/WHEEL
calar-2.5.1.dist-info/top_level.txt
calar-2.5.1.dist-info/RECORD
