Metadata-Version: 2.1
Name: calar
Version: 2.5.1
Summary: The text colorizer everyone needs!
Home-page: https://github.com/calar
Author: calar
Author-email: calar.dev@gmail.com
License: MIT
Classifier: License :: OSI Approved :: MIT License
Classifier: Programming Language :: Python :: 3
Classifier: Programming Language :: Python :: 3.7
Classifier: Development Status :: 5 - Production/Stable
Classifier: Development Status :: 4 - Beta
Classifier: Development Status :: 3 - Alpha
Classifier: Development Status :: 2 - Pre-Alpha
Classifier: Development Status :: 1 - Planning
Classifier: Operating System :: OS Independent
Classifier: Topic :: Software Development :: Libraries :: Python Modules
Classifier: Intended Audience :: Developers
Requires-Python: >=3.7
Requires-Dist: pygments
